jsonc_reflection/__init__.py
jsonc_reflection/reflection.py
jsonc_reflection/__internal/libjsonc.dll
jsonc_reflection/__internal/native_lib.py
jsonc_reflection/__pyinstaller/__init__.py
jsonc_reflection/__pyinstaller/hook-jsonc_reflection.py
tests/test.py
jsonc_reflection-1.0.0.dist-info/METADATA
jsonc_reflection-1.0.0.dist-info/WHEEL
jsonc_reflection-1.0.0.dist-info/entry_points.txt
jsonc_reflection-1.0.0.dist-info/top_level.txt
jsonc_reflection-1.0.0.dist-info/RECORD
