Metadata-Version: 2.4
Name: jsonc_reflection
Version: 1.0.0
Summary: Jsonc Reflection Library
Author: GlacieTeam
License: MPL-2.0
Classifier: Programming Language :: Python
